CHANGES
CONTRIBUTORS.txt
LICENSE
README.txt
bootstrap.py
buildout.cfg
setup.cfg
setup.py
collective/__init__.py
collective.dist.egg-info/PKG-INFO
collective.dist.egg-info/SOURCES.txt
collective.dist.egg-info/dependency_links.txt
collective.dist.egg-info/entry_points.txt
collective.dist.egg-info/namespace_packages.txt
collective.dist.egg-info/not-zip-safe
collective.dist.egg-info/requires.txt
collective.dist.egg-info/top_level.txt
collective/dist/README.txt
collective/dist/__init__.py
collective/dist/check.py
collective/dist/core.py
collective/dist/mregister.py
collective/dist/mupload.py
collective/dist/pypirc.py
collective/dist/docs/README.txt
collective/dist/doctests/README.txt
collective/dist/tests/__init__.py
collective/dist/tests/test_check.py
collective/dist/tests/test_distdocs.py
collective/dist/tests/test_distdocstrings.py
collective/dist/tests/test_mregister.py
collective/dist/tests/test_mupload.py
collective/dist/tests/test_pypirc.py