Metadata-Version: 1.0
Name: collective.dist
Version: 0.2.4
Summary: Distutils commands to upload files to several servers
Home-page: http://svn.plone.org/svn/collective/collective.dist
Author: Tarek Ziade
Author-email: support@ingeniweb.com
License: GPL
Keywords: pypi setuptools distutils
Platform: UNKNOWN
Classifier: Programming Language :: Python
Classifier: Topic :: Software Development :: Libraries :: Python Modules
